README.md
dhcpain.py
setup.py
dhcpain.egg-info/PKG-INFO
dhcpain.egg-info/SOURCES.txt
dhcpain.egg-info/dependency_links.txt
dhcpain.egg-info/entry_points.txt
dhcpain.egg-info/requires.txt
dhcpain.egg-info/top_level.txt