Metadata-Version: 1.1
Name: dhcpain
Version: 1.0.0
Summary: DHCP Exhaustion utility
Home-page: https://github.com/GoodiesHQ/DHCPain/
Author: Austin Archer
Author-email: aarcher73k@gmail.com
License: UNKNOWN
Platform: UNKNOWN
Classifier: License :: OSI Approved :: GNU Affero General Public License v3
Classifier: Topic :: Security
Classifier: Topic :: System :: Networking
